RockPhyRoll/__init__.py
RockPhyRoll/rockphyroll.py
RockPhyRoll-0.0.2.dist-info/LICENSE.txt
RockPhyRoll-0.0.2.dist-info/METADATA
RockPhyRoll-0.0.2.dist-info/WHEEL
RockPhyRoll-0.0.2.dist-info/top_level.txt
RockPhyRoll-0.0.2.dist-info/RECORD
