Metadata-Version: 2.1
Name: RockPhyRoll
Version: 0.0.2
Summary: RockPhyRoll, Rock'n'Roll.
Home-page: UNKNOWN
Author: Jiaxin Yu
Author-email: yujiaxin666@outlook.com
License: GNU GPLv3
Requires-Dist: numpy
